{
  "sample_idx": 735,
  "original_image_path": "/data/Asan_DP/Yonsei/New_pipe/Young_Kang_won_pipe/2025/2025\ub144/9163985_\uae40\ubd09\uc220/ipeak_capture_YS25-20122_IgA.png",
  "target": [
    0.0,
    0.0
  ],
  "prediction": [
    false,
    false
  ],
  "probability": [
    0.07018115371465683,
    0.19178318977355957
  ],
  "is_correct": true,
  "class_names": [
    "Linear Pattern",
    "Peri-vascular Pattern"
  ],
  "class_results": {
    "Linear Pattern": {
      "target": 0.0,
      "prediction": 0.0,
      "probability": 0.07018115371465683,
      "correct": 1.0
    },
    "Peri-vascular Pattern": {
      "target": 0.0,
      "prediction": 0.0,
      "probability": 0.19178318977355957,
      "correct": 1.0
    }
  }
}